gitcraft-0.1.4.data/scripts/gitcraft.exe
gitcraft-0.1.4.dist-info/METADATA
gitcraft-0.1.4.dist-info/WHEEL
gitcraft-0.1.4.dist-info/licenses/LICENSE
gitcraft/__init__.py
gitcraft-0.1.4.dist-info/RECORD
