Metadata-Version: 2.4
Name: gitcraft
Version: 0.1.4
Classifier: License :: OSI Approved :: Apache Software License
Classifier: Programming Language :: Rust
Classifier: Programming Language :: Python :: 3
Classifier: Operating System :: OS Independent
Classifier: Environment :: Console
License-File: LICENSE
Summary: A template project for GitHub-related utilities.
Author-email: John Kagunda <john@kagunda.dev>
License: Apache-2.0
Requires-Python: >=3.8
